rating_orders/__init__.py
rating_orders-0.1.dist-info/LICENCE.txt
rating_orders-0.1.dist-info/METADATA
rating_orders-0.1.dist-info/WHEEL
rating_orders-0.1.dist-info/top_level.txt
rating_orders-0.1.dist-info/RECORD
