Metadata-Version: 2.2
Name: rating_orders
Version: 0.1
Summary: This package related to ratings on orders
Author: Sreeja
Author-email: sreeja4518@gmail.com
Classifier: Programming Language :: Python :: 3
Classifier: License :: OSI Approved :: MIT License
Classifier: Operating System :: OS Independent
License-File: LICENCE.txt
Dynamic: author
Dynamic: author-email
Dynamic: classifier
Dynamic: summary
